{"meta": {"names": 70, "pairs": 109, "ranked": 93, "breadth": 89, "win": "Jun-2022 to Jun-2026", "entry": "~2023 to 2026 (\u226518m P/E baseline before each entry)"}, "pair_ic": {"1": {"ic": 0.046, "t": 1.68, "pos": 56, "nm": 48}, "3": {"ic": 0.072, "t": 2.67, "pos": 70, "nm": 46}, "6": {"ic": 0.061, "t": 1.89, "pos": 63, "nm": 43}, "12": {"ic": 0.044, "t": 1.48, "pos": 65, "nm": 37}}, "pair_cond": {"1": {"dm": 1.09, "dh": 56, "dn": 886, "pm": -0.23, "ph": 51, "pn": 1229, "mm": -0.06}, "3": {"dm": 2.88, "dh": 59, "dn": 838, "pm": -0.99, "ph": 52, "pn": 1166, "mm": -0.05}, "6": {"dm": 4.54, "dh": 58, "dn": 761, "pm": -0.62, "ph": 50, "pn": 1072, "mm": -0.49}, "12": {"dm": 4.94, "dh": 54, "dn": 640, "pm": -0.78, "ph": 50, "pn": 903, "mm": -0.95}}, "pair_dec": {"1": [{"lo": -3.68, "hi": -1.52, "mean": 1.33, "n": 454}, {"lo": -1.52, "hi": -0.98, "mean": 0.78, "n": 454}, {"lo": -0.98, "hi": -0.54, "mean": 0.22, "n": 455}, {"lo": -0.54, "hi": -0.17, "mean": -0.34, "n": 454}, {"lo": -0.17, "hi": 0.2, "mean": 0.34, "n": 455}, {"lo": 0.2, "hi": 0.54, "mean": -0.29, "n": 454}, {"lo": 0.54, "hi": 0.89, "mean": -0.14, "n": 454}, {"lo": 0.89, "hi": 1.29, "mean": -0.09, "n": 455}, {"lo": 1.29, "hi": 1.77, "mean": -0.13, "n": 454}, {"lo": 1.77, "hi": 4.01, "mean": -0.53, "n": 455}], "3": [{"lo": -3.68, "hi": -1.52, "mean": 2.56, "n": 432}, {"lo": -1.52, "hi": -0.97, "mean": 2.74, "n": 433}, {"lo": -0.96, "hi": -0.54, "mean": 0.75, "n": 432}, {"lo": -0.54, "hi": -0.17, "mean": 0.69, "n": 433}, {"lo": -0.17, "hi": 0.19, "mean": -0.74, "n": 433}, {"lo": 0.19, "hi": 0.53, "mean": -1.25, "n": 432}, {"lo": 0.53, "hi": 0.89, "mean": 0.7, "n": 433}, {"lo": 0.89, "hi": 1.28, "mean": -1.04, "n": 432}, {"lo": 1.28, "hi": 1.75, "mean": -0.64, "n": 433}, {"lo": 1.75, "hi": 4.01, "mean": -1.11, "n": 433}], "6": [{"lo": -3.68, "hi": -1.51, "mean": 3.47, "n": 399}, {"lo": -1.51, "hi": -0.95, "mean": 5.32, "n": 400}, {"lo": -0.95, "hi": -0.53, "mean": 0.59, "n": 400}, {"lo": -0.53, "hi": -0.15, "mean": 0.9, "n": 400}, {"lo": -0.15, "hi": 0.2, "mean": -2.14, "n": 400}, {"lo": 0.21, "hi": 0.53, "mean": -2.45, "n": 400}, {"lo": 0.53, "hi": 0.88, "mean": 0.33, "n": 400}, {"lo": 0.88, "hi": 1.28, "mean": -0.39, "n": 400}, {"lo": 1.28, "hi": 1.74, "mean": 0.14, "n": 400}, {"lo": 1.74, "hi": 4.01, "mean": -1.43, "n": 400}], "12": [{"lo": -3.68, "hi": -1.52, "mean": 4.16, "n": 336}, {"lo": -1.52, "hi": -0.95, "mean": 5.67, "n": 336}, {"lo": -0.95, "hi": -0.53, "mean": -1.02, "n": 336}, {"lo": -0.53, "hi": -0.16, "mean": 0.71, "n": 337}, {"lo": -0.16, "hi": 0.21, "mean": -2.45, "n": 336}, {"lo": 0.21, "hi": 0.54, "mean": -2.78, "n": 336}, {"lo": 0.54, "hi": 0.89, "mean": -0.3, "n": 337}, {"lo": 0.89, "hi": 1.27, "mean": 1.07, "n": 336}, {"lo": 1.27, "hi": 1.73, "mean": 1.33, "n": 336}, {"lo": 1.73, "hi": 4.01, "mean": -4.23, "n": 337}]}, "pair_port": {"sharpe": 1.02, "mean": 0.543, "vol": 1.842, "hit": 58, "n": 48, "eq": [1.0218, 1.0323, 1.0274, 1.0534, 1.0861, 1.1013, 1.1635, 1.1771, 1.1491, 1.1378, 1.1328, 1.1146, 1.1583, 1.1717, 1.1694, 1.1661, 1.1905, 1.2069, 1.2398, 1.2486, 1.3047, 1.3155, 1.2625, 1.2456, 1.2499, 1.2405, 1.2354, 1.2718, 1.2713, 1.2921, 1.2945, 1.2978, 1.2994, 1.2856, 1.3087, 1.333, 1.3013, 1.3053, 1.2853, 1.2988, 1.2871, 1.2786, 1.2836, 1.2765, 1.2811, 1.2675, 1.3006, 1.2865], "mon": ["2022-07", "2022-08", "2022-09", "2022-10", "2022-11", "2022-12", "2023-01", "2023-02", "2023-03", "2023-04", "2023-05", "2023-06", "2023-07", "2023-08", "2023-09", "2023-10", "2023-11", "2023-12", "2024-01", "2024-02", "2024-03", "2024-04", "2024-05", "2024-06", "2024-07", "2024-08", "2024-09", "2024-10", "2024-11", "2024-12", "2025-01", "2025-02", "2025-03", "2025-04", "2025-05", "2025-06", "2025-07", "2025-08", "2025-09", "2025-10", "2025-11", "2025-12", "2026-01", "2026-02", "2026-03", "2026-04", "2026-05", "2026-06"]}, "sn_ic": {"1": {"ic": 0.026, "t": 1.49, "pos": 52, "nm": 48}, "3": {"ic": 0.039, "t": 2.79, "pos": 59, "nm": 46}, "6": {"ic": 0.032, "t": 1.83, "pos": 51, "nm": 43}, "12": {"ic": 0.001, "t": 0.07, "pos": 49, "nm": 37}}, "sn_cond": {"1": {"cm": 0.17, "ch": 50, "cn": 912, "rm": -0.23, "rh": 52, "rn": 398}, "3": {"cm": 0.52, "ch": 51, "cn": 849, "rm": -1.1, "rh": 56, "rn": 389}, "6": {"cm": 0.66, "ch": 52, "cn": 752, "rm": -1.84, "rh": 59, "rn": 379}, "12": {"cm": -0.23, "ch": 50, "cn": 691, "rm": -2.88, "rh": 57, "rn": 292}}, "perpair": [{"a": "ARES US", "b": "TPG US", "ic": 0.66, "n": 25, "cz": 1.14, "d6": null}, {"a": "AB US", "b": "BLK US", "ic": 0.66, "n": 37, "cz": -0.51, "d6": 3.6}, {"a": "EVR US", "b": "LAZ US", "ic": 0.63, "n": 37, "cz": 1.75, "d6": 25.3}, {"a": "APO US", "b": "CG US", "ic": 0.62, "n": 37, "cz": 1.19, "d6": null}, {"a": "EXPN LN", "b": "TRU US", "ic": 0.6, "n": 37, "cz": -0.69, "d6": null}, {"a": "APO US", "b": "BX US", "ic": 0.6, "n": 37, "cz": 1.1, "d6": 35.8}, {"a": "MC US", "b": "PWP US", "ic": 0.59, "n": 33, "cz": -0.29, "d6": null}, {"a": "CBOE US", "b": "CME US", "ic": 0.56, "n": 37, "cz": 0.73, "d6": null}, {"a": "WISE LN", "b": "WU US", "ic": 0.56, "n": 30, "cz": 0.18, "d6": 41.5}, {"a": "AB US", "b": "IVZ US", "ic": 0.56, "n": 37, "cz": -1.4, "d6": 1.6}, {"a": "CME US", "b": "NDAQ US", "ic": 0.54, "n": 37, "cz": -0.64, "d6": 8.5}, {"a": "BLK US", "b": "IVZ US", "ic": 0.54, "n": 37, "cz": -1.51, "d6": 7.6}, {"a": "APO US", "b": "TPG US", "ic": 0.53, "n": 25, "cz": 2.41, "d6": null}, {"a": "LPLA US", "b": "SCHW US", "ic": 0.52, "n": 37, "cz": -0.18, "d6": null}, {"a": "BX US", "b": "TPG US", "ic": 0.51, "n": 25, "cz": 1.33, "d6": null}, {"a": "SCHW US", "b": "SF US", "ic": 0.5, "n": 37, "cz": -1.86, "d6": 3.4}, {"a": "BX US", "b": "KKR US", "ic": 0.49, "n": 37, "cz": -0.24, "d6": -5.2}, {"a": "ICG LN", "b": "PGHN SW", "ic": 0.45, "n": 37, "cz": 2.64, "d6": 25.4}, {"a": "ADYEN NA", "b": "PYPL US", "ic": 0.44, "n": 37, "cz": -0.93, "d6": 22.4}, {"a": "LAZ US", "b": "PIPR US", "ic": 0.44, "n": 37, "cz": -1.15, "d6": -7.6}, {"a": "LPLA US", "b": "RJF US", "ic": 0.44, "n": 37, "cz": -2.44, "d6": 16.6}, {"a": "KKR US", "b": "OWL US", "ic": 0.43, "n": 32, "cz": 1.82, "d6": null}, {"a": "AB US", "b": "BEN US", "ic": 0.43, "n": 37, "cz": -2.56, "d6": 4.0}, {"a": "AMUN FP", "b": "DWS GY", "ic": 0.42, "n": 37, "cz": -0.65, "d6": -1.1}, {"a": "CME US", "b": "ICE US", "ic": 0.41, "n": 37, "cz": 0.66, "d6": 2.0}, {"a": "ICE US", "b": "NDAQ US", "ic": 0.4, "n": 37, "cz": -1.66, "d6": 8.0}, {"a": "MCO US", "b": "SPGI US", "ic": 0.38, "n": 37, "cz": 2.05, "d6": null}, {"a": "CG US", "b": "TPG US", "ic": 0.38, "n": 25, "cz": 1.57, "d6": 16.6}, {"a": "CBOE US", "b": "NDAQ US", "ic": 0.37, "n": 37, "cz": 0.27, "d6": null}, {"a": "PJT US", "b": "PWP US", "ic": 0.37, "n": 33, "cz": 0.41, "d6": null}, {"a": "LPLA US", "b": "SF US", "ic": 0.37, "n": 37, "cz": -1.95, "d6": 21.9}, {"a": "EVR US", "b": "PIPR US", "ic": 0.36, "n": 37, "cz": 1.55, "d6": 9.8}, {"a": "APO US", "b": "KKR US", "ic": 0.35, "n": 37, "cz": 1.63, "d6": 10.2}, {"a": "OWL US", "b": "TPG US", "ic": 0.35, "n": 25, "cz": -1.49, "d6": -0.5}, {"a": "MKTX US", "b": "TW US", "ic": 0.34, "n": 37, "cz": -1.57, "d6": -8.3}, {"a": "HLI US", "b": "MC US", "ic": 0.34, "n": 37, "cz": -0.55, "d6": 3.0}, {"a": "KKR US", "b": "TPG US", "ic": 0.34, "n": 25, "cz": 1.37, "d6": null}, {"a": "EFX US", "b": "TRU US", "ic": 0.33, "n": 37, "cz": -0.15, "d6": null}, {"a": "AB US", "b": "TROW US", "ic": 0.33, "n": 37, "cz": -0.04, "d6": 3.2}, {"a": "BEN US", "b": "BLK US", "ic": 0.33, "n": 37, "cz": 2.41, "d6": 8.0}, {"a": "RJF US", "b": "SF US", "ic": 0.33, "n": 37, "cz": -0.42, "d6": 2.2}, {"a": "DB1 GY", "b": "LSEG LN", "ic": 0.32, "n": 37, "cz": 2.24, "d6": null}, {"a": "MA US", "b": "V US", "ic": 0.32, "n": 37, "cz": -1.97, "d6": null}, {"a": "LAZ US", "b": "PWP US", "ic": 0.32, "n": 33, "cz": 0.01, "d6": -2.9}, {"a": "HLI US", "b": "PWP US", "ic": 0.31, "n": 33, "cz": -1.28, "d6": 14.0}, {"a": "BX US", "b": "CG US", "ic": 0.31, "n": 37, "cz": -0.16, "d6": null}, {"a": "RJF US", "b": "SCHW US", "ic": 0.31, "n": 37, "cz": 2.11, "d6": null}, {"a": "ARES US", "b": "OWL US", "ic": 0.29, "n": 32, "cz": 1.84, "d6": null}, {"a": "EFX US", "b": "EXPN LN", "ic": 0.28, "n": 37, "cz": 0.44, "d6": null}, {"a": "EVR US", "b": "PJT US", "ic": 0.26, "n": 37, "cz": 1.75, "d6": 19.3}, {"a": "EVR US", "b": "MC US", "ic": 0.25, "n": 37, "cz": 1.68, "d6": 17.5}, {"a": "MC US", "b": "PIPR US", "ic": 0.25, "n": 37, "cz": -1.06, "d6": -4.5}, {"a": "PIPR US", "b": "PJT US", "ic": 0.25, "n": 37, "cz": 0.77, "d6": 5.6}, {"a": "MC US", "b": "PJT US", "ic": 0.24, "n": 37, "cz": -0.81, "d6": 2.3}, {"a": "APO US", "b": "ARES US", "ic": 0.24, "n": 37, "cz": 1.14, "d6": 8.3}, {"a": "BX US", "b": "OWL US", "ic": 0.23, "n": 32, "cz": 2.12, "d6": null}, {"a": "FDS US", "b": "MSCI US", "ic": 0.22, "n": 37, "cz": -2.4, "d6": -20.0}, {"a": "IBKR US", "b": "SCHW US", "ic": 0.22, "n": 37, "cz": 2.83, "d6": 31.0}, {"a": "FISV US", "b": "GPN US", "ic": 0.21, "n": 37, "cz": -0.11, "d6": null}, {"a": "HLI US", "b": "LAZ US", "ic": 0.2, "n": 37, "cz": -1.09, "d6": 9.7}, {"a": "BEN US", "b": "IVZ US", "ic": 0.2, "n": 37, "cz": 1.11, "d6": 5.1}, {"a": "LAZ US", "b": "MC US", "ic": 0.17, "n": 37, "cz": 0.24, "d6": -1.1}, {"a": "CG US", "b": "OWL US", "ic": 0.17, "n": 32, "cz": 2.19, "d6": null}, {"a": "CBOE US", "b": "ICE US", "ic": 0.16, "n": 37, "cz": 1.69, "d6": null}, {"a": "ENX FP", "b": "LSEG LN", "ic": 0.16, "n": 37, "cz": 2.53, "d6": 12.2}, {"a": "FOUR US", "b": "XYZ US", "ic": 0.16, "n": 37, "cz": -1.83, "d6": 15.8}, {"a": "CPAY US", "b": "WEX US", "ic": 0.16, "n": 37, "cz": 2.12, "d6": 18.4}, {"a": "EVR US", "b": "HLI US", "ic": 0.16, "n": 37, "cz": 2.74, "d6": 16.8}, {"a": "FDS US", "b": "SPGI US", "ic": 0.15, "n": 37, "cz": -1.8, "d6": -6.9}, {"a": "ADYEN NA", "b": "XYZ US", "ic": 0.15, "n": 37, "cz": -0.39, "d6": null}, {"a": "EVR US", "b": "PWP US", "ic": 0.15, "n": 33, "cz": 2.13, "d6": null}, {"a": "ARES US", "b": "BX US", "ic": 0.14, "n": 37, "cz": -0.06, "d6": null}, {"a": "ARES US", "b": "KKR US", "ic": 0.13, "n": 37, "cz": -0.33, "d6": null}, {"a": "CG US", "b": "KKR US", "ic": 0.13, "n": 37, "cz": -0.02, "d6": -7.7}, {"a": "BLK US", "b": "TROW US", "ic": 0.13, "n": 37, "cz": 0.37, "d6": 10.5}, {"a": "MSCI US", "b": "SPGI US", "ic": 0.12, "n": 37, "cz": 0.4, "d6": -1.0}, {"a": "HLI US", "b": "PJT US", "ic": 0.12, "n": 37, "cz": -1.74, "d6": -3.4}, {"a": "EQT SS", "b": "ICG LN", "ic": 0.09, "n": 37, "cz": -0.98, "d6": 1.8}, {"a": "ARES US", "b": "CG US", "ic": 0.08, "n": 37, "cz": -0.16, "d6": null}, {"a": "HLI US", "b": "PIPR US", "ic": 0.06, "n": 37, "cz": -2.15, "d6": -2.5}, {"a": "LAZ US", "b": "PJT US", "ic": 0.05, "n": 37, "cz": -0.53, "d6": -8.1}, {"a": "HLNE US", "b": "STEP US", "ic": 0.04, "n": 37, "cz": -1.2, "d6": -5.2}, {"a": "BGN IM", "b": "FBK IM", "ic": 0.03, "n": 37, "cz": 1.36, "d6": null}, {"a": "PIPR US", "b": "PWP US", "ic": -0.02, "n": 33, "cz": 1.16, "d6": null}, {"a": "FBK IM", "b": "FTK GY", "ic": -0.03, "n": 37, "cz": -0.91, "d6": -14.4}, {"a": "DB1 GY", "b": "ENX FP", "ic": -0.04, "n": 37, "cz": -1.1, "d6": -0.4}, {"a": "EQT SS", "b": "PGHN SW", "ic": -0.04, "n": 37, "cz": 0.54, "d6": 4.2}, {"a": "APO US", "b": "OWL US", "ic": -0.1, "n": 32, "cz": 2.43, "d6": null}, {"a": "PYPL US", "b": "XYZ US", "ic": -0.12, "n": 37, "cz": 0.06, "d6": null}, {"a": "FIS US", "b": "GPN US", "ic": -0.13, "n": 37, "cz": 0.48, "d6": 20.9}, {"a": "BEN US", "b": "TROW US", "ic": -0.18, "n": 37, "cz": 2.44, "d6": null}, {"a": "FIS US", "b": "FISV US", "ic": -0.19, "n": 37, "cz": 0.83, "d6": -11.5}, {"a": "IVZ US", "b": "TROW US", "ic": -0.28, "n": 37, "cz": 1.14, "d6": null}], "trap": {"rho": 0.5, "disc": {"1": {"all": {"m": 1.09, "h": 56, "n": 886}, "tc": {"m": 1.46, "h": 58, "n": 565}, "rb": {"m": 0.45, "h": 51, "n": 321}}, "3": {"all": {"m": 2.88, "h": 59, "n": 838}, "tc": {"m": 3.54, "h": 62, "n": 532}, "rb": {"m": 1.74, "h": 54, "n": 306}}, "6": {"all": {"m": 4.54, "h": 58, "n": 761}, "tc": {"m": 5.71, "h": 61, "n": 479}, "rb": {"m": 2.54, "h": 54, "n": 282}}, "12": {"all": {"m": 4.94, "h": 54, "n": 640}, "tc": {"m": 5.42, "h": 54, "n": 412}, "rb": {"m": 4.06, "h": 54, "n": 228}}}}, "cost": {"turn": 0.498, "short": 0.5, "n": 48, "gross": {"sharpe": 1.02, "mean": 0.543}, "net_10_50": {"sharpe": 0.89, "mean": 0.472}, "eqg": [1.0218, 1.0323, 1.0274, 1.0534, 1.0861, 1.1013, 1.1635, 1.1771, 1.1491, 1.1378, 1.1328, 1.1146, 1.1583, 1.1717, 1.1694, 1.1661, 1.1905, 1.2069, 1.2398, 1.2486, 1.3047, 1.3155, 1.2625, 1.2456, 1.2499, 1.2405, 1.2354, 1.2718, 1.2713, 1.2921, 1.2945, 1.2978, 1.2994, 1.2856, 1.3087, 1.333, 1.3013, 1.3053, 1.2853, 1.2988, 1.2871, 1.2786, 1.2836, 1.2765, 1.2811, 1.2675, 1.3006, 1.2865], "mon": ["2022-07", "2022-08", "2022-09", "2022-10", "2022-11", "2022-12", "2023-01", "2023-02", "2023-03", "2023-04", "2023-05", "2023-06", "2023-07", "2023-08", "2023-09", "2023-10", "2023-11", "2023-12", "2024-01", "2024-02", "2024-03", "2024-04", "2024-05", "2024-06", "2024-07", "2024-08", "2024-09", "2024-10", "2024-11", "2024-12", "2025-01", "2025-02", "2025-03", "2025-04", "2025-05", "2025-06", "2025-07", "2025-08", "2025-09", "2025-10", "2025-11", "2025-12", "2026-01", "2026-02", "2026-03", "2026-04", "2026-05", "2026-06"]}}